registry/__init__.py
registry/companyregister.py
mca_company_register-1.6.0.dist-info/METADATA
mca_company_register-1.6.0.dist-info/WHEEL
mca_company_register-1.6.0.dist-info/top_level.txt
mca_company_register-1.6.0.dist-info/RECORD
