Metadata-Version: 2.1
Name: mca-company-register
Version: 1.6.0
Summary: AE ops
Home-page: https://github.com/bharath-sadhu/mca-company-registry.git
Author: bharath sadhu
Author-email: bharath.sadhu@cloudwick.com
License: UNKNOWN
Keywords: Company Registry
Platform: UNKNOWN
Classifier: Intended Audience :: Developers
Classifier: Programming Language :: Python :: 3
Classifier: Programming Language :: Python :: 3.7
Requires-Dist: fastapi
Requires-Dist: pydantic
